interactive_figure/__about__.py
interactive_figure/__init__.py
interactive_figure/interactive_figure.py
interactive_figure-0.4.1.dist-info/METADATA
interactive_figure-0.4.1.dist-info/WHEEL
interactive_figure-0.4.1.dist-info/licenses/LICENSE.txt
interactive_figure-0.4.1.dist-info/RECORD
