Metadata-Version: 2.3
Name: interactive-figure
Version: 0.4.1
Summary: Create interactive Matplotlib figures!
Project-URL: Documentation, https://teuncm.github.io/interactive-figure/autoapi/interactive_figure/interactive_figure/index.html
Project-URL: Issues, https://github.com/teuncm/interactive-figure/issues
Project-URL: Source, https://github.com/teuncm/interactive-figure
Author-email: Teun Mathijssen <teun.c.mathijssen@gmail.com>
License-Expression: MIT
License-File: LICENSE.txt
Classifier: Framework :: Matplotlib
Classifier: Intended Audience :: Education
Classifier: Intended Audience :: Science/Research
Classifier: Programming Language :: Python
Classifier: Programming Language :: Python :: 3
Classifier: Topic :: Scientific/Engineering :: Visualization
Requires-Python: >=3.9
Requires-Dist: matplotlib
